{
  "url": "https://cinemm.com/_next/static/chunks/main-app-528bd41f5c5a1ef7.js",
  "method": "GET",
  "status": 200,
  "headers": {
    "cache-control": "public, max-age=0, must-revalidate",
    "nel": "{\"report_to\":\"cf-nel\",\"success_fraction\":0.0,\"max_age\":604800}",
    "content-encoding": "zstd",
    "cf-cache-status": "HIT",
    "etag": "W/\"02e1e10392cbc0eef69075daf430414d\"",
    "report-to": "{\"group\":\"cf-nel\",\"max_age\":604800,\"endpoints\":[{\"url\":\"https://a.nel.cloudflare.com/report/v4?s=Lo%2F5gQPBCZXQqHaKp4awBNxtKNmLjSFNSsUe60cCaMwf42HAkHc2BmG4tgHihrZMzvFss64rtcaPhrY%2BZPj6MGj2NIgqhDObhhuiG2GK5%2Bu9eOR5%2FpVRUdds14ND\"}]}",
    "cf-ray": "a1751e941a883c34-BOM",
    "alt-svc": "h3=\":443\"; ma=86400",
    "date": "Tue, 07 Jul 2026 07:26:10 GMT",
    "content-type": "text/javascript",
    "server": "cloudflare"
  }
}